{
  "id": "pf2e-community-monster-core-token-pack-mapping",
  "title": "PF2e Community Monster Core Token Pack Mapping",
  "version": "1.0.0",
  "compatibility": {
    "minimum": "11.315",
    "verified": "11.315"
  },
  "authors": [
    {
      "name": "Emmanuel Wineberg",
      "discord": "esheyw",
      "email": "esheyw@gmail.com",
      "url": "https://github.com/esheyw"
    },
    {
      "name": "Symon S.",
      "discord": "symons."
    }
  ],
  "relationships": {
    "systems": [
      {
        "id": "pf2e",
        "type": "system",
        "compatibility": {
          "minimum": "5.15"
        }
      }
    ],
    "requires": [
      {
        "id": "pf2e-tokens-bestiaries",
        "type": "module",
        "compatibility": {}
      }
    ]
  },
  "media": [
    {
      "type": "setup",
      "caption": "Token Pack Mapping"
    }
  ],
  "flags": {
    "pf2e-community-monster-core-token-pack-mapping": {
      "pf2e-art": "mapping.json"
    }
  },
  "manifest": "updatedByRelease",
  "download": "updatedByRelease",
  "readme": "https://github.com/esheyw/pf2e-community-monster-core-token-pack-mapping/blob/main/README.md",
  "url": "https://github.com/esheyw/pf2e-community-monster-core-token-pack-mapping/",
  "bugs": "https://github.com/esheyw/pf2e-community-monster-core-token-pack-mapping/issues",
  "changelog": "https://github.com/esheyw/pf2e-community-monster-core-token-pack-mapping/blob/main/CHANGELOG.md"
}
